+evnt/install.m
+evnt/quakeio.m
+evnt/read.m
+evnt/write.m
cpp/CMakeLists.txt
cpp/Makefile
cpp/PeerMotion.cpp
cpp/PeerMotion.h
cpp/PeerNGA.cpp
cpp/PeerNGAMotion.cpp
cpp/PeerNGAMotion.h
cpp/Vector.cpp
cpp/Vector.h
cpp/blasdecl.h
cpp/elementAPI.h
cpp/http.c
cpp/http.h
cpp/main.cpp
evnt/__init__.py
evnt/__main__.py
evnt/brace2.mplstyle
evnt/core.py
evnt/elcentro.AT2
evnt/elcentro.py
evnt/obs.py
evnt/processing.py
evnt/svg.py
evnt/vega.py
evnt/parse/__init__.py
evnt/parse/basic_formats.py
evnt/parse/cosmos.py
evnt/parse/csmip.py
evnt/parse/eqsig.py
evnt/parse/nga.py
evnt/parse/opensees.py
evnt/parse/smc.py
evnt/utils/__init__.py
evnt/utils/parseutils.py
evnt/utils/processing.py
evnt/utils/spectrum.py
evnt-0.0.1.dist-info/METADATA
evnt-0.0.1.dist-info/WHEEL
evnt-0.0.1.dist-info/entry_points.txt
evnt-0.0.1.dist-info/top_level.txt
evnt-0.0.1.dist-info/RECORD
