Metadata-Version: 2.1
Name: evnt
Version: 0.0.1
Summary: Ground motion file parsing.
Author-email: "Claudio M. Perez" <50180406+claudioperez@users.noreply.github.com>, Chrystal Chern <52893467+chrystalchern@users.noreply.github.com>
Project-URL: Repository, http://github.com/claudioperez/evnt
Keywords: seismic,pre-processing,finite-element-analysis
Classifier: Development Status :: 4 - Beta
Classifier: Intended Audience :: Science/Research
Classifier: Intended Audience :: Developers
Classifier: License :: OSI Approved :: BSD License
Classifier: Programming Language :: Python
Classifier: Programming Language :: Python :: 3
Classifier: Programming Language :: Python :: 3.7
Classifier: Programming Language :: Python :: 3.8
Classifier: Programming Language :: Python :: 3.9
Classifier: Programming Language :: Python :: 3.10
Classifier: Programming Language :: Python :: 3.11
Classifier: Programming Language :: Python :: 3.12
Classifier: Programming Language :: Python :: 3 :: Only
Classifier: Topic :: Software Development
Classifier: Topic :: Scientific/Engineering
Classifier: Operating System :: Microsoft :: Windows
Classifier: Operating System :: POSIX
Classifier: Operating System :: Unix
Classifier: Operating System :: MacOS
Requires-Dist: opensees
Requires-Dist: scipy
Requires-Dist: numpy
Requires-Dist: sees
